hack4u/__init__.py
hack4u/courses.py
hack4u/utils.py
packSanti-0.1.0.dist-info/METADATA
packSanti-0.1.0.dist-info/WHEEL
packSanti-0.1.0.dist-info/top_level.txt
packSanti-0.1.0.dist-info/RECORD
