Metadata-Version: 2.1
Name: packSanti
Version: 0.1.0
Summary: Prueba
Home-page: http://wwww.ucm.es
Author: Sudosu
